python_lambda_builder/__init__.py
python_lambda_builder/build.py
python_lambda_builder/enums.py
python_lambda_builder/pip_build.py
python_lambda_builder/poetry_build.py
python_lambda_builder/utils.py
python_lambda_builder-0.1.1.dist-info/entry_points.txt
python_lambda_builder-0.1.1.dist-info/WHEEL
python_lambda_builder-0.1.1.dist-info/METADATA
python_lambda_builder-0.1.1.dist-info/RECORD
