Metadata-Version: 2.1
Name: python-lambda-builder
Version: 0.1.1
Summary: A CLI application for building lambda python functions and dependencies
Author: Damilola Adeyemi
Author-email: adeyemidamilola3@gmail.com
Requires-Python: >=3.8,<4.0
Classifier: Programming Language :: Python :: 3
Classifier: Programming Language :: Python :: 3.10
Classifier: Programming Language :: Python :: 3.8
Classifier: Programming Language :: Python :: 3.9
Requires-Dist: toml (>=0.10.2,<0.11.0)
Requires-Dist: typer[all] (>=0.5.0,<0.6.0)
